mh/__init__.py
mh/mh.py
mh-0.0.33.data/scripts/README.md
mhlib/__init__.py
mhlib/eg.py
mhlib/l2/__init__.py
mhlib/l2/l2.py
mh-0.0.33.dist-info/LICENSE
mh-0.0.33.dist-info/METADATA
mh-0.0.33.dist-info/WHEEL
mh-0.0.33.dist-info/top_level.txt
mh-0.0.33.dist-info/RECORD
