Metadata-Version: 2.1
Name: mh
Version: 0.0.33
Summary: A small example package
Home-page: https://github.com/markhallett/mh
Author: Mark Hallett
Author-email: mh@markhallett.co.uk
Project-URL: Documentation, https://markhallett.github.io/mh
Classifier: Programming Language :: Python :: 3
Classifier: Programming Language :: Python :: 3.6
Classifier: Programming Language :: Python :: 3.7
Classifier: License :: OSI Approved :: MIT License
Classifier: Operating System :: OS Independent
Provides-Extra: dev
License-File: LICENSE
